README.md
setup.py
fu/__init__.py
fu/conftest.py
fu/futils.py
fu/incremental_rename.py
fu/iterate_files.py
fu/prefix.py
fu/commands/__init__.py
fu/commands/base_command.py
fu/commands/tv_show/__init__.py
fu/commands/tv_show/app.py
fu/commands/tv_show/fix_names.py
fu/common/__init__.py
fu/common/dateutils.py
fu/common/errors.py
fu/exif/__init__.py
fu/exif/app.py
fu/exif/errors.py
fu/exif/fix_exif.py
fu/exif/inspect_datetime.py
fu/exif/inspector.py
fu/exif/ls.py
fu/exif/models.py
fu/imgresize/__init__.py
fu/imgresize/resizer.py
fu/index/__init__.py
fu/index/idx_svc.py
fu/movie/__init__.py
fu/movie/fixname.py
fu/tvshow/__init__.py
fu/tvshow/fixname.py
fu/utils/__init__.py
fu/utils/console.py
fu/utils/date.py
fu/utils/path.py
futils.egg-info/PKG-INFO
futils.egg-info/SOURCES.txt
futils.egg-info/dependency_links.txt
futils.egg-info/entry_points.txt
futils.egg-info/requires.txt
futils.egg-info/top_level.txt