Metadata-Version: 2.1
Name: futils
Version: 1.3.3
Summary: A cli tool for managing documents and media files
Home-page: https://github.com/giobyte8/futils
Author: Giovanni Aguirre
Author-email: giovanni.fi05@gmail.com
License: UNKNOWN
Platform: UNKNOWN
Classifier: Development Status :: 5 - Production/Stable
Classifier: Intended Audience :: End Users/Desktop
Classifier: License :: OSI Approved :: BSD License
Classifier: Natural Language :: English
Classifier: Programming Language :: Python :: 3
Classifier: Programming Language :: Python :: 3.7
